README.md
setup.cfg
setup.py
app/__init__.py
app/main.py
flask_xd.egg-info/PKG-INFO
flask_xd.egg-info/SOURCES.txt
flask_xd.egg-info/dependency_links.txt
flask_xd.egg-info/entry_points.txt
flask_xd.egg-info/requires.txt
flask_xd.egg-info/top_level.txt