Metadata-Version: 1.1
Name: flask-xd
Version: 1.0
Summary: Setup a flask template with or without auth/user services
Home-page: UNKNOWN
Author: Xzavier Dunn
Author-email: UNKNOWN
License: MIT
Download-URL: https://github.com/XzavierDunn/flask-templates/archive/v1.0.tar.gz
Platform: UNKNOWN
